LICENSE
LICENSE.txt
README.md
setup.cfg
setup.py
YahooRequest.egg-info/PKG-INFO
YahooRequest.egg-info/SOURCES.txt
YahooRequest.egg-info/dependency_links.txt
YahooRequest.egg-info/entry_points.txt
YahooRequest.egg-info/requires.txt
YahooRequest.egg-info/top_level.txt
yahoorequests/__init__.py
yahoorequests/yahoorequests.py